sms/__init__.py
sms/message.py
sms/signals.py
sms/utils.py
sms/backends/__init__.py
sms/backends/base.py
sms/backends/console.py
sms/backends/dummy.py
sms/backends/filebased.py
sms/backends/locmem.py
sms/backends/messagebird.py
sms/backends/twilio.py
django_sms-0.7.0.dist-info/LICENSE
django_sms-0.7.0.dist-info/LICENSE.django
django_sms-0.7.0.dist-info/METADATA
django_sms-0.7.0.dist-info/WHEEL
django_sms-0.7.0.dist-info/top_level.txt
django_sms-0.7.0.dist-info/RECORD
