Metadata-Version: 2.1
Name: django-sms
Version: 0.7.0
Summary: A Django app for sending SMS with interchangeable backends.
Home-page: https://github.com/django-enterprise/django-sms
Author: Roald Nefs
Author-email: info@roaldnefs.com
License: BSD-3-Clause
Platform: any
Classifier: Development Status :: 5 - Production/Stable
Classifier: Environment :: Web Environment
Classifier: Framework :: Django
Classifier: Framework :: Django :: 3.2
Classifier: Framework :: Django :: 4.1
Classifier: Framework :: Django :: 4.2
Classifier: Framework :: Django :: 5.0
Classifier: Intended Audience :: Developers
Classifier: Natural Language :: English
Classifier: License :: OSI Approved :: BSD License
Classifier: Operating System :: OS Independent
Classifier: Programming Language :: Python
Classifier: Programming Language :: Python :: 3
Classifier: Programming Language :: Python :: 3.8
Classifier: Programming Language :: Python :: 3.9
Classifier: Programming Language :: Python :: 3.10
Classifier: Programming Language :: Python :: 3.11
Classifier: Programming Language :: Python :: 3.12
License-File: LICENSE
License-File: LICENSE.django
Requires-Dist: Django >=3.2
Provides-Extra: messagebird
Requires-Dist: messagebird ; extra == 'messagebird'
Provides-Extra: twilio
Requires-Dist: twilio ; extra == 'twilio'
